zipapps/__init__.py
zipapps/__main__.py
zipapps/activate_zipapps.py
zipapps/download_python.py
zipapps/ensure_zipapps.py.template
zipapps/entry_point.py.template
zipapps/freezing.py
zipapps/main.py
zipapps-2025.9.4.dist-info/licenses/LICENSE
zipapps-2025.9.4.dist-info/METADATA
zipapps-2025.9.4.dist-info/WHEEL
zipapps-2025.9.4.dist-info/entry_points.txt
zipapps-2025.9.4.dist-info/top_level.txt
zipapps-2025.9.4.dist-info/RECORD
